brainscore_language/__init__.py
brainscore_language/__main__.py
brainscore_language/artificial_subject.py
brainscore_language/benchmark_helpers/__init__.py
brainscore_language/benchmarks/blank2014/__init__.py
brainscore_language/benchmarks/blank2014/benchmark.py
brainscore_language/benchmarks/blank2014/ceiling.py
brainscore_language/benchmarks/blank2014/test.py
brainscore_language/benchmarks/fedorenko2016/__init__.py
brainscore_language/benchmarks/fedorenko2016/benchmark.py
brainscore_language/benchmarks/futrell2018/__init__.py
brainscore_language/benchmarks/futrell2018/benchmark.py
brainscore_language/benchmarks/futrell2018/test.py
brainscore_language/benchmarks/pereira2018/__init__.py
brainscore_language/benchmarks/pereira2018/benchmark.py
brainscore_language/benchmarks/pereira2018/ceiling_packaging.py
brainscore_language/benchmarks/pereira2018/test.py
brainscore_language/benchmarks/syntaxgym/README.md
brainscore_language/benchmarks/syntaxgym/__init__.py
brainscore_language/benchmarks/syntaxgym/benchmark.py
brainscore_language/benchmarks/syntaxgym/gpt2_precomputed.py
brainscore_language/benchmarks/syntaxgym/requirements.txt
brainscore_language/benchmarks/syntaxgym/sg_prediction.py
brainscore_language/benchmarks/syntaxgym/sg_suite.py
brainscore_language/benchmarks/syntaxgym/test.py
brainscore_language/benchmarks/syntaxgym/test_suites.json
brainscore_language/benchmarks/syntaxgym/suites/syntaxgym-2020/center_embed.json
brainscore_language/benchmarks/syntaxgym/suites/syntaxgym-2020/center_embed_mod.json
brainscore_language/benchmarks/syntaxgym/suites/syntaxgym-2020/cleft.json
brainscore_language/benchmarks/syntaxgym/suites/syntaxgym-2020/cleft_modifier.json
brainscore_language/benchmarks/syntaxgym/suites/syntaxgym-2020/fgd_hierarchy.json
brainscore_language/benchmarks/syntaxgym/suites/syntaxgym-2020/fgd_object.json
brainscore_language/benchmarks/syntaxgym/suites/syntaxgym-2020/fgd_pp.json
brainscore_language-2.2.1.dist-info/licenses/LICENSE
brainscore_language-2.2.1.dist-info/METADATA
brainscore_language-2.2.1.dist-info/WHEEL
brainscore_language-2.2.1.dist-info/top_level.txt
brainscore_language-2.2.1.dist-info/RECORD
