Metadata-Version: 2.4
Name: brainscore_language
Version: 2.2.1
License: MIT License
Requires-Python: >=3.11
License-File: LICENSE
Requires-Dist: tqdm
Requires-Dist: numpy>=1.21
Requires-Dist: brainscore-core
Requires-Dist: fire
Requires-Dist: scikit-learn
Requires-Dist: torch>=1.9.1
Requires-Dist: transformers>=4.11.3
Requires-Dist: gensim
Requires-Dist: joblib
Requires-Dist: requests
Provides-Extra: test
Requires-Dist: pytest; extra == "test"
Requires-Dist: pytest-check<=1.3.0; extra == "test"
Dynamic: license-file
